vaultconfig/__init__.py
vaultconfig/_version.py
vaultconfig/cli.py
vaultconfig/config.py
vaultconfig/crypt.py
vaultconfig/exceptions.py
vaultconfig/obscure.py
vaultconfig/py.typed
vaultconfig/schema.py
vaultconfig/formats/__init__.py
vaultconfig/formats/base.py
vaultconfig/formats/ini_format.py
vaultconfig/formats/toml_format.py
vaultconfig/formats/yaml_format.py
vaultconfig-0.2.1.dist-info/licenses/LICENSE
vaultconfig-0.2.1.dist-info/METADATA
vaultconfig-0.2.1.dist-info/WHEEL
vaultconfig-0.2.1.dist-info/entry_points.txt
vaultconfig-0.2.1.dist-info/top_level.txt
vaultconfig-0.2.1.dist-info/RECORD
