Metadata-Version: 2.4
Name: vaultconfig
Version: 0.2.1
Summary: Secure configuration management library with encryption support for Python
Author-email: Holger Nahrstaedt <nahrstaedt@gmail.com>
License: MIT License
Requires-Python: >=3.9
License-File: LICENSE
Requires-Dist: click>=8.0.0
Requires-Dist: rich>=13.0.0
Requires-Dist: cryptography>=41.0.0
Requires-Dist: PyNaCl>=1.5.0
Requires-Dist: tomli>=1.2.0; python_version < "3.11"
Requires-Dist: tomli-w>=1.0.0
Requires-Dist: pydantic>=2.0.0
Provides-Extra: yaml
Requires-Dist: PyYAML>=6.0; extra == "yaml"
Provides-Extra: dev
Requires-Dist: pytest>=7.0.0; extra == "dev"
Requires-Dist: ruff>=0.1.0; extra == "dev"
Requires-Dist: PyYAML>=6.0; extra == "dev"
Dynamic: license-file
